Workbook

Sheet Order Data
A1: Order ID | B1: Salesperson ID | C1: Order Date | D1: Product | E1: Category | F1: Quantity | G1: Unit Price ($) | H1: Discount % | I1: Order Amount ($) | J1: Discount Amount ($) | K1: Net Amount ($) | L1: Region | M1: Sales person ID status | N1: Discount category | O1: Salesperson Name
A2: ORD-0001 | B2: SP011 | C2: 45349 | D2: Laptop | E2: Electronics | F2: 9 | G2: 527.54 | H2: 0 | I2: =F2*G2 -> 4747.86 | J2: =I2*H2 -> 0 | K2: =I2-J2 -> 4747.86 | L2: =_xlfn.XLOOKUP(B2,'Salesperson Master'!$A:$A,'Salesperson Master'!$C:$C,"Not Found") -> East | M2: =IF(B2="","ID not present","ID is present") -> ID is present | N2: =IF(H2>=0.15,"High",IF(0.5<=H2<=0.15,"Medium","Low")) -> Low | O2: =_xlfn.XLOOKUP(B2, 'Salesperson Master'!A:A, 'Salesperson Master'!B:B) -> Karen Harris
A3: ORD-0002 | B3: SP012 | C3: 45344 | D3: Tablet | E3: Electronics | F3: 18 | G3: 219.53 | H3: 0.1 | I3: =F3*G3 -> 3951.54 | J3: =I3*H3 -> 395.154 | K3: =I3-J3 -> 3556.386 | L3: =_xlfn.XLOOKUP(B3,'Salesperson Master'!$A:$A,'Salesperson Master'!$C:$C,"Not Found") -> West | M3: =IF(B3="","ID not present","ID is present") -> ID is present | N3: =IF(H3>=0.15,"High",IF(0.5<=H3<=0.15,"Medium","Low")) -> Low | O3: =_xlfn.XLOOKUP(B3, 'Salesperson Master'!A:A, 'Salesperson Master'!B:B) -> Leo Martinez
A4: ORD-0003 | B4: SP001 | C4: 45307 | D4: Monitor | E4: Electronics | F4: 7 | G4: 503.69 | H4: 0.15 | I4: =F4*G4 -> 3525.83 | J4: =I4*H4 -> 528.8745 | K4: =I4-J4 -> 2996.9555 | L4: =_xlfn.XLOOKUP(B4,'Salesperson Master'!$A:$A,'Salesperson Master'!$C:$C,"Not Found") -> North | M4: =IF(B4="","ID not present","ID is present") -> ID is present | N4: =IF(H4>=0.15,"High",IF(0.5<=H4<=0.15,"Medium","Low")) -> High | O4: =_xlfn.XLOOKUP(B4, 'Salesperson Master'!A:A, 'Salesperson Master'!B:B) -> Alice Johnson
A5: ORD-0004 | B5: SP001 | C5: 45579 | D5: Mouse | E5: Accessories | F5: 18 | G5: 868.06 | H5: 0.1 | I5: =F5*G5 -> 15625.08 | J5: =I5*H5 -> 1562.508 | K5: =I5-J5 -> 14062.572 | L5: =_xlfn.XLOOKUP(B5,'Salesperson Master'!$A:$A,'Salesperson Master'!$C:$C,"Not Found") -> North | M5: =IF(B5="","ID not present","ID is present") -> ID is present | N5: =IF(H5>=0.15,"High",IF(0.5<=H5<=0.15,"Medium","Low")) -> Low | O5: =_xlfn.XLOOKUP(B5, 'Salesperson Master'!A:A, 'Salesperson Master'!B:B) -> Alice Johnson
A6: ORD-0005 | B6: SP010 | C6: 45434 | D6: Charger | E6: Accessories | F6: 1 | G6: 1529.67 | H6: 0 | I6: =F6*G6 -> 1529.67 | J6: =I6*H6 -> 0 | K6: =I6-J6 -> 1529.67 | L6: =_xlfn.XLOOKUP(B6,'Salesperson Master'!$A:$A,'Salesperson Master'!$C:$C,"Not Found") -> South | M6: =IF(B6="","ID not present","ID is present") -> ID is present | N6: =IF(H6>=0.15,"High",IF(0.5<=H6<=0.15,"Medium","Low")) -> Low | O6: =_xlfn.XLOOKUP(B6, 'Salesperson Master'!A:A, 'Salesperson Master'!B:B) -> James White
A7: ORD-0006 | B7: SP012 | C7: 45508 | D7: Webcam | E7: Electronics | F7: 9 | G7: 353.19 | H7: 0.25 | I7: =F7*G7 -> 3178.71 | J7: =I7*H7 -> 794.6775 | K7: =I7-J7 -> 2384.0325 | L7: =_xlfn.XLOOKUP(B7,'Salesperson Master'!$A:$A,'Salesperson Master'!$C:$C,"Not Found") -> West | M7: =IF(B7="","ID not present","ID is present") -> ID is present | N7: =IF(H7>=0.15,"High",IF(0.5<=H7<=0.15,"Medium","Low")) -> High | O7: =_xlfn.XLOOKUP(B7, 'Salesperson Master'!A:A, 'Salesperson Master'!B:B) -> Leo Martinez
A8: ORD-0007 | B8: SP006 | C8: 45344 | D8: Monitor | E8: Electronics | F8: 13 | G8: 238.6 | H8: 0.25 | I8: =F8*G8 -> 3101.8 | J8: =I8*H8 -> 775.45 | K8: =I8-J8 -> 2326.35 | L8: =_xlfn.XLOOKUP(B8,'Salesperson Master'!$A:$A,'Salesperson Master'!$C:$C,"Not Found") -> South | M8: =IF(B8="","ID not present","ID is present") -> ID is present | N8: =IF(H8>=0.15,"High",IF(0.5<=H8<=0.15,"Medium","Low")) -> High | O8: =_xlfn.XLOOKUP(B8, 'Salesperson Master'!A:A, 'Salesperson Master'!B:B) -> Frank Wilson
A9: ORD-0008 | B9: SP006 | C9: 45601 | D9: Headset | E9: Accessories | F9: 2 | G9: 1472.98 | H9: 0.15 | I9: =F9*G9 -> 2945.96 | J9: =I9*H9 -> 441.894 | K9: =I9-J9 -> 2504.066 | L9: =_xlfn.XLOOKUP(B9,'Salesperson Master'!$A:$A,'Salesperson Master'!$C:$C,"Not Found") -> South | M9: =IF(B9="","ID not present","ID is present") -> ID is present | N9: =IF(H9>=0.15,"High",IF(0.5<=H9<=0.15,"Medium","Low")) -> High | O9: =_xlfn.XLOOKUP(B9, 'Salesperson Master'!A:A, 'Salesperson Master'!B:B) -> Frank Wilson
A10: ORD-0009 | B10: SP002 | C10: 45485 | D10: Monitor | E10: Electronics | F10: 18 | G10: 621.7 | H10: 0.2 | I10: =F10*G10 -> 11190.6 | J10: =I10*H10 -> 2238.12 | K10: =I10-J10 -> 8952.48 | L10: =_xlfn.XLOOKUP(B10,'Salesperson Master'!$A:$A,'Salesperson Master'!$C:$C,"Not Found") -> South | M10: =IF(B10="","ID not present","ID is present") -> ID is present | N10: =IF(H10>=0.15,"High",IF(0.5<=H10<=0.15,"Medium","Low")) -> High | O10: =_xlfn.XLOOKUP(B10, 'Salesperson Master'!A:A, 'Salesperson Master'!B:B) -> Bob Martinez
A11: ORD-0010 | B11: SP010 | C11: 45477 | D11: Scanner | E11: Office | F11: 7 | G11: 1423.92 | H11: 0 | I11: =F11*G11 -> 9967.44 | J11: =I11*H11 -> 0 | K11: =I11-J11 -> 9967.44 | L11: =_xlfn.XLOOKUP(B11,'Salesperson Master'!$A:$A,'Salesperson Master'!$C:$C,"Not Found") -> South | M11: =IF(B11="","ID not present","ID is present") -> ID is present | N11: =IF(H11>=0.15,"High",IF(0.5<=H11<=0.15,"Medium","Low")) -> Low | O11: =_xlfn.XLOOKUP(B11, 'Salesperson Master'!A:A, 'Salesperson Master'!B:B) -> James White
A12: ORD-0011 | B12: SP011 | C12: 45408 | D12: Charger | E12: Accessories | F12: 10 | G12: 1971.18 | H12: 0.25 | I12: =F12*G12 -> 19711.8 | J12: =I12*H12 -> 4927.95 | K12: =I12-J12 -> 14783.85 | L12: =_xlfn.XLOOKUP(B12,'Salesperson Master'!$A:$A,'Salesperson Master'!$C:$C,"Not Found") -> East | M12: =IF(B12="","ID not present","ID is present") -> ID is present | N12: =IF(H12>=0.15,"High",IF(0.5<=H12<=0.15,"Medium","Low")) -> High | O12: =_xlfn.XLOOKUP(B12, 'Salesperson Master'!A:A, 'Salesperson Master'!B:B) -> Karen Harris
A13: ORD-0012 | B13: SP004 | C13: 45343 | D13: Desk Chair | E13: Furniture | F13: 9 | G13: 934.15 | H13: 0.25 | I13: =F13*G13 -> 8407.35 | J13: =I13*H13 -> 2101.8375 | K13: =I13-J13 -> 6305.5125 | L13: =_xlfn.XLOOKUP(B13,'Salesperson Master'!$A:$A,'Salesperson Master'!$C:$C,"Not Found") -> West | M13: =IF(B13="","ID not present","ID is present") -> ID is present | N13: =IF(H13>=0.15,"High",IF(0.5<=H13<=0.15,"Medium","Low")) -> High | O13: =_xlfn.XLOOKUP(B13, 'Salesperson Master'!A:A, 'Salesperson Master'!B:B) -> David Kim
... A101: ORD-0100 | B101: SP004 | C101: 45636 | D101: Headset | E101: Accessories | F101: 8 | G101: 1622.8 | H101: 0 | I101: =F101*G101 -> 12982.4 | J101: =I101*H101 -> 0 | K101: =I101-J101 -> 12982.4 | L101: =_xlfn.XLOOKUP(B101,'Salesperson Master'!$A:$A,'Salesperson Master'!$C:$C,"Not Found") -> West | M101: =IF(B101="","ID not present","ID is present") -> ID is present | N101: =IF(H101>=0.15,"High",IF(0.5<=H101<=0.15,"Medium","Low")) -> Low | O101: =_xlfn.XLOOKUP(B101, 'Salesperson Master'!A:A, 'Salesperson Master'!B:B) -> David Kim

Sheet Salesperson Master
A1: Salesperson ID | B1: Salesperson Name | C1: Region
A2: SP001 | B2: Alice Johnson | C2: North
A3: SP002 | B3: Bob Martinez | C3: South
A4: SP003 | B4: Carol Lee | C4: East
A5: SP004 | B5: David Kim | C5: West
A6: SP005 | B6: Eva Brown | C6: North
A7: SP006 | B7: Frank Wilson | C7: South
A8: SP007 | B8: Grace Chen | C8: East
A9: SP008 | B9: Henry Davis | C9: West
A10: SP009 | B10: Iris Thompson | C10: North
A11: SP010 | B11: James White | C11: South
A12: SP011 | B12: Karen Harris | C12: East
... A16: SP015 | B16: Olivia Walker | C16: East

Sheet Discount per region
A2: Total Discount Amount By Region
A3: Row Labels | B3: Sum of Discount Amount ($) | C3: Average of Discount %
A4: East | B4: 48942.916 | C4: 0.13103448
A5: North | B5: 26235.786 | C5: 0.1037037
A6: South | B6: 25099.175 | C6: 0.13181818
A7: West | B7: 20177.05 | C7: 0.11590909
A8: Grand Total | B8: 120454.93 | C8: 0.1205

Sheet  Regenew trend
C1: Monthly revenue trend for each product
A3: Sum of Net Amount ($) | B3: Column Labels
B4: Jan | C4: Feb | D4: Mar | E4: Apr | F4: May | G4: Jun | H4: Jul | I4: Aug | J4: Sep | K4: Oct | L4: Nov | M4: Dec | N4: Grand Total
A6: Row Labels
A7: Charger | C7: 5620.6845 | D7: 10612.56 | E7: 14783.85 | F7: 4178.217 | G7: 23089.537 | I7: 5898.2 | K7: 9073.575 | N7: 73256.624
A8: Desk Chair | B8: 12532.792 | C8: 6305.5125 | F8: 21718.53 | M8: 3129.84 | N8: 43686.675
A9: Headset | D9: 2256.41 | E9: 11536.931 | F9: 12686.464 | L9: 2504.066 | M9: 17813.402 | N9: 46797.273
A10: Keyboard | D10: 30341.6 | F10: 44260.547 | I10: 6426.81 | K10: 27693.37 | N10: 108722.33
A11: Laptop | C11: 4747.86 | E11: 5499.6165 | F11: 559.65 | I11: 13129.965 | J11: 5585.22 | K11: 1509.7445 | N11: 31032.056
A12: Monitor | B12: 29033.208 | C12: 10288.965 | E12: 2737.8 | H12: 17513.918 | L12: 15849.372 | M12: 2828.55 | N12: 78251.812
A13: Mouse | B13: 4085.0325 | C13: 34400.239 | F13: 1808.6385 | G13: 9737.4425 | H13: 5217.9 | K13: 28034.442 | N13: 83283.694
A14: Printer | C14: 4269.816 | D14: 26603.317 | E14: 19173.36 | G14: 12829.18 | I14: 29132.08 | K14: 4440.4 | L14: 9469.2005 | N14: 105917.35
A15: Router | G15: 8256.885 | H15: 3605.8 | J15: 11799.043 | M15: 4177.125 | N15: 27838.854
A16: Scanner | C16: 7602.945 | E16: 409.728 | G16: 14779.71 | H16: 19243.64 | I16: 3981.1195 | K16: 9471.627 | N16: 55488.77
A17: Smartphone | C17: 19695 | F17: 14300.017 | M17: 10011.366 | N17: 44006.384
A18: Standing Desk | C18: 3469.248 | D18: 21755.07 | M18: 18461.352 | N18: 43685.67
A19: Tablet | B19: 538.208 | C19: 3556.386 | D19: 1448.112 | F19: 2514.878 | H19: 7126.425 | M19: 3713.43 | N19: 18897.439
A20: USB Hub | B20: 7197.16 | E20: 26442.592 | J20: 17502.4 | K20: 642.56 | M20: 12523.32 | N20: 64308.032
A21: Webcam | D21: 5227.356 | I21: 23875.566 | L21: 28060.717 | N21: 57163.64
A22: Grand Total | B22: 53386.401 | C22: 99956.656 | D22: 98244.425 | E22: 80583.878 | F22: 102026.94 | G22: 68692.755 | H22: 52707.683 | I22: 82443.74 | J22: 34886.664 | K22: 80865.718 | L22: 55883.356 | M22: 72658.385 | N22: 882336.6
A25: Row Labels | B25: Sum of Net Amount ($)
A26: Jan | B26: 53386.401
A27: Feb | B27: 99956.656
A28: Mar | B28: 98244.425
A29: Apr | B29: 80583.878
A30: May | B30: 102026.94
A31: Jun | B31: 68692.755
A32: Jul | B32: 52707.683
A33: Aug | B33: 82443.74
A34: Sep | B34: 34886.664
A35: Oct | B35: 80865.718
A36: Nov | B36: 55883.356
A37: Dec | B37: 72658.385
A38: Grand Total | B38: 882336.6

Sheet Sales performance
A3: Row Labels | B3: Sum of Net Amount ($)
A4: Noah Lewis | B4: 24552.964
A5: James White | B5: 32579.025
A6: Frank Wilson | B6: 34160.245
A7: Mia Clark | B7: 41705.034
A8: Grace Chen | B8: 51024.201
A9: Henry Davis | B9: 52660.325
A10: Alice Johnson | B10: 54256.07
A11: Olivia Walker | B11: 57535.618
A12: Leo Martinez | B12: 63711.976
A13: Iris Thompson | B13: 65775.1
A14: Bob Martinez | B14: 72152.31
A15: David Kim | B15: 74668.559
... A19: Grand Total | B19: 882336.6

Sheet KPI
A3: Sum of Net Amount ($) | B3: Sum of Order Amount ($) | C3: Sum of Discount Amount ($) | D3: Average of Discount % | E3: Count of Order ID | F3: Sum of Quantity | H3: Value for Display
A4: 882336.6 | B4: 1002791.5 | C4: 120454.93 | D4: 0.1205 | E4: 100 | F4: 1032 | H4: Net amount | I4: Order amount | J4: Discount amt | K4: Avg of Discount | L4: Order id count | M4: Total Product Count
H5: =GETPIVOTDATA("Sum of Net Amount ($)",$A$3) -> 882336.6 | I5: =GETPIVOTDATA("Sum of Order Amount ($)",$A$3) -> 1002791.5 | J5: =GETPIVOTDATA("Sum of Discount Amount ($)",$A$3) -> 120454.93 | K5: =GETPIVOTDATA("Average of Discount %",$A$3) -> 0.1205 | L5: =GETPIVOTDATA("Count of Order ID",$A$3) -> 100 | M5: =GETPIVOTDATA("Sum of Quantity",$A$3) -> 1032

Sheet Dash board
X30: s
